Metadata-Version: 2.1
Name: phase_curve
Version: 0.1.0
Summary:  Lightweight, bare bones asteroid phase curve fitter 
Home-page: https://github.com/bernardinelli/phase_curve
Author: Pedro Bernardinelli
Author-email: phbern@uw.edu
Classifier: Programming Language :: Python :: 3
Classifier: Operating System :: OS Independent
Classifier: License :: OSI Approved :: MIT License
Requires-Python: >=3.6
License-File: LICENSE
Requires-Dist: numpy
Requires-Dist: scipy
